cyberspacy/__init__.py
cyberspacy/about.py
cyberspacy/expressions.py
cyberspacy/lemmatizer.py
cyberspacy/processor.py
cyberspacy/stemmer.py
cyberspacy/tagger.py
cyberspacy/tokenizer.py
tests/__init__.py
tests/test_commandline.py
tests/test_detections.py
cyberspacy-1.1.1.dist-info/LICENSE
cyberspacy-1.1.1.dist-info/METADATA
cyberspacy-1.1.1.dist-info/WHEEL
cyberspacy-1.1.1.dist-info/top_level.txt
cyberspacy-1.1.1.dist-info/RECORD
