Metadata-Version: 2.1
Name: cyberspacy
Version: 1.1.1
Summary: spaCy pipeline component for adding cyber meta data to Doc, Token and Span objects.
Home-page: https://github.com/gclen/cyberspacy
Author: Graham Clendenning
Author-email: gclendenning271@gmail.com
License: MIT
Platform: UNKNOWN
Requires-Dist: spacy (<3.0.0,>=2.0.0)
